smumerix-0.2.0.dist-info/METADATA
smumerix-0.2.0.dist-info/WHEEL
smumerix/preex.pyi
smumerix/py.typed
smumerix/smumerix.pyi
smumerix/__init__.py
smumerix/smumerix.cp311-win_amd64.pyd
smumerix-0.2.0.dist-info/RECORD
